dsna_ml/__init__.py
dsna_ml/generate.py
dsna_ml/process.py
dsna_ml/test.py
dsna_ml/train.py
dsna_ml-0.0.0.dist-info/METADATA
dsna_ml-0.0.0.dist-info/WHEEL
dsna_ml-0.0.0.dist-info/top_level.txt
dsna_ml-0.0.0.dist-info/RECORD
