Metadata-Version: 2.1
Name: dsna-ml
Version: 0.0.0
Summary: "Automate machine learning"
Requires-Python: >=3.10
Requires-Dist: numpy (==1.24.3)
Requires-Dist: pandas (==1.4.3)
Requires-Dist: pmdarima (==2.0.3)
Requires-Dist: prophet (==1.1.4)
Requires-Dist: scikit-learn (==1.2.2)
Requires-Dist: tensorflow (==2.13.0rc1)
Requires-Dist: xgboost (==1.7.6)
